odoo/addons/base_import_module_group/README.rst
odoo/addons/base_import_module_group/__init__.py
odoo/addons/base_import_module_group/__manifest__.py
odoo/addons/base_import_module_group/i18n/base_import_module_group.pot
odoo/addons/base_import_module_group/models/__init__.py
odoo/addons/base_import_module_group/models/ir_module.py
odoo/addons/base_import_module_group/readme/CONTRIBUTORS.rst
odoo/addons/base_import_module_group/readme/DESCRIPTION.rst
odoo/addons/base_import_module_group/security/res_groups.xml
odoo/addons/base_import_module_group/static/description/icon.png
odoo/addons/base_import_module_group/static/description/index.html
odoo/addons/base_import_module_group/views/import_module_group.xml
odoo12_addon_base_import_module_group-12.0.1.0.1.dist-info/METADATA
odoo12_addon_base_import_module_group-12.0.1.0.1.dist-info/WHEEL
odoo12_addon_base_import_module_group-12.0.1.0.1.dist-info/top_level.txt
odoo12_addon_base_import_module_group-12.0.1.0.1.dist-info/RECORD
